[
    {
        "domain": "072545.magicremedyshop.ru",
        "count": "4",
        "first_seen": "2015-05-17 17:47:00",
        "last_seen": "2015-05-17 20:07:48",
        "ip_address": "91.200.12.17",
        "type": "IPv4"
    },
    {
        "domain": "072545.magicremedyshop.ru",
        "count": "4",
        "first_seen": "2015-05-17 23:26:10",
        "last_seen": "2015-05-18 00:16:20",
        "ip_address": "95.84.156.43",
        "type": "IPv4"
    },
    {
        "domain": "072545.magicremedyshop.ru",
        "count": "3",
        "first_seen": "2015-05-17 13:26:15",
        "last_seen": "2015-05-17 19:33:41",
        "ip_address": "217.174.100.238",
        "type": "IPv4"
    }
]