[
    {
        "domain": "5949310283.newaidpurchase.ru",
        "count": "4",
        "first_seen": "2015-05-25 14:13:06",
        "last_seen": "2015-05-26 04:28:28",
        "ip_address": "81.21.193.71",
        "type": "IPv4"
    },
    {
        "domain": "5949310283.newaidpurchase.ru",
        "count": "4",
        "first_seen": "2015-06-02 11:24:12",
        "last_seen": "2015-06-02 19:46:29",
        "ip_address": "91.200.12.17",
        "type": "IPv4"
    },
    {
        "domain": "5949310283.newaidpurchase.ru",
        "count": "2",
        "first_seen": "2015-05-25 15:49:34",
        "last_seen": "2015-05-25 15:49:34",
        "ip_address": "95.31.192.232",
        "type": "IPv4"
    },
    {
        "domain": "5949310283.newaidpurchase.ru",
        "count": "2",
        "first_seen": "2015-05-30 11:23:32",
        "last_seen": "2015-05-30 11:23:32",
        "ip_address": "95.84.156.43",
        "type": "IPv4"
    }
]