[
    {
        "domain": "6527463117.newaidpurchase.ru",
        "count": "4",
        "first_seen": "2015-05-24 04:42:47",
        "last_seen": "2015-05-24 18:16:29",
        "ip_address": "65.110.39.50",
        "type": "IPv4"
    },
    {
        "domain": "6527463117.newaidpurchase.ru",
        "count": "5",
        "first_seen": "2015-05-24 11:14:08",
        "last_seen": "2015-05-24 15:35:13",
        "ip_address": "91.200.12.17",
        "type": "IPv4"
    },
    {
        "domain": "6527463117.newaidpurchase.ru",
        "count": "6",
        "first_seen": "2015-05-24 20:11:16",
        "last_seen": "2015-05-25 02:39:13",
        "ip_address": "91.213.233.72",
        "type": "IPv4"
    },
    {
        "domain": "6527463117.newaidpurchase.ru",
        "count": "3",
        "first_seen": "2015-05-24 19:33:33",
        "last_seen": "2015-05-24 19:33:56",
        "ip_address": "95.31.192.232",
        "type": "IPv4"
    }
]