[
    {
        "domain": "dv92hlyta0.newaidpurchase.ru",
        "count": "8",
        "first_seen": "2015-05-24 14:31:10",
        "last_seen": "2015-05-24 23:01:16",
        "ip_address": "78.239.188.233",
        "type": "IPv4"
    },
    {
        "domain": "dv92hlyta0.newaidpurchase.ru",
        "count": "4",
        "first_seen": "2015-05-24 22:15:33",
        "last_seen": "2015-05-25 00:03:11",
        "ip_address": "91.213.233.72",
        "type": "IPv4"
    },
    {
        "domain": "dv92hlyta0.newaidpurchase.ru",
        "count": "3",
        "first_seen": "2015-05-24 14:31:11",
        "last_seen": "2015-05-24 19:00:56",
        "ip_address": "95.31.192.232",
        "type": "IPv4"
    },
    {
        "domain": "dv92hlyta0.newaidpurchase.ru",
        "count": "3",
        "first_seen": "2015-05-24 19:33:44",
        "last_seen": "2015-05-24 19:33:45",
        "ip_address": "95.84.156.43",
        "type": "IPv4"
    },
    {
        "domain": "dv92hlyta0.newaidpurchase.ru",
        "count": "2",
        "first_seen": "2015-05-25 02:00:53",
        "last_seen": "2015-05-25 02:00:53",
        "ip_address": "203.192.247.59",
        "type": "IPv4"
    }
]