[
    {
        "domain": "e.blogfatburngron.ru",
        "count": "2",
        "first_seen": "2013-10-13 16:39:49",
        "last_seen": "2013-10-14 02:22:30",
        "ip_address": "111.121.193.199",
        "type": "IPv4"
    },
    {
        "domain": "e.blogfatburngron.ru",
        "count": "2",
        "first_seen": "2013-10-13 16:39:49",
        "last_seen": "2013-10-14 02:22:30",
        "ip_address": "111.121.193.200",
        "type": "IPv4"
    },
    {
        "domain": "e.blogfatburngron.ru",
        "count": "2",
        "first_seen": "2013-10-13 16:39:49",
        "last_seen": "2013-10-14 02:22:30",
        "ip_address": "119.1.109.40",
        "type": "IPv4"
    },
    {
        "domain": "e.blogfatburngron.ru",
        "count": "2",
        "first_seen": "2013-10-13 16:39:49",
        "last_seen": "2013-10-14 02:22:30",
        "ip_address": "119.1.109.48",
        "type": "IPv4"
    }
]