[
    {
        "domain": "ebion.shop",
        "count": "2",
        "first_seen": "2018-05-09 20:06:18",
        "last_seen": "2018-05-09 20:06:18",
        "ip_address": "50.63.202.56",
        "type": "IPv4"
    },
    {
        "domain": "ebion.shop",
        "count": "9",
        "first_seen": "2018-05-23 20:06:08",
        "last_seen": "2018-06-17 16:36:01",
        "ip_address": "69.172.201.153",
        "type": "IPv4"
    },
    {
        "domain": "ebion.shop",
        "count": "30",
        "first_seen": "2021-08-24 06:31:53",
        "last_seen": "2021-08-30 03:51:20",
        "ip_address": "104.223.15.169",
        "type": "IPv4"
    },
    {
        "domain": "ebion.shop",
        "count": "1",
        "first_seen": "2018-05-01 09:26:25",
        "last_seen": "2018-05-01 09:26:25",
        "ip_address": "184.168.221.38",
        "type": "IPv4"
    },
    {
        "domain": "ebion.shop",
        "count": "2",
        "first_seen": "2018-05-06 00:16:47",
        "last_seen": "2018-05-06 00:16:47",
        "ip_address": "184.168.221.41",
        "type": "IPv4"
    },
    {
        "domain": "ebion.shop",
        "count": "2",
        "first_seen": "2018-04-26 13:09:51",
        "last_seen": "2018-04-26 13:09:51",
        "ip_address": "184.168.221.61",
        "type": "IPv4"
    },
    {
        "domain": "ebion.shop",
        "count": "2",
        "first_seen": "2018-05-06 00:20:14",
        "last_seen": "2018-05-06 00:20:14",
        "ip_address": "184.168.221.63",
        "type": "IPv4"
    }
]