[
    {
        "domain": "infore.backlinksninja.com",
        "count": "167",
        "first_seen": "2022-08-10 16:17:30",
        "last_seen": "2022-08-31 01:36:15",
        "ip_address": "167.160.189.156",
        "type": "IPv4"
    },
    {
        "domain": "infore.backlinksninja.com",
        "count": "36",
        "first_seen": "2022-12-17 08:22:36",
        "last_seen": "2023-11-01 12:55:52",
        "ip_address": "204.11.56.48",
        "type": "IPv4"
    },
    {
        "domain": "infore.backlinksninja.com",
        "count": "6",
        "first_seen": "2023-12-08 15:43:00",
        "last_seen": "2023-12-31 08:10:43",
        "ip_address": "208.91.197.46",
        "type": "IPv4"
    },
    {
        "domain": "infore.backlinksninja.com",
        "count": "1",
        "first_seen": "2023-10-24 14:18:11",
        "last_seen": "2023-10-24 14:18:11",
        "ip_address": "204.11.56.48",
        "type": "IPv4"
    }
]