[
    {
        "domain": "istaliya.com",
        "count": "736",
        "first_seen": "2018-04-04 18:01:47",
        "last_seen": "2019-06-02 11:53:57",
        "ip_address": "94.73.147.216",
        "type": "IPv4"
    },
    {
        "domain": "istaliya.com",
        "count": "30",
        "first_seen": "2019-10-18 04:16:40",
        "last_seen": "2019-11-09 09:20:05",
        "ip_address": "156.234.36.206",
        "type": "IPv4"
    },
    {
        "domain": "istaliya.com",
        "count": "162",
        "first_seen": "2016-11-05 23:57:00",
        "last_seen": "2018-03-30 18:30:04",
        "ip_address": "195.142.1.93",
        "type": "IPv4"
    },
    {
        "domain": "istaliya.com",
        "count": "2",
        "first_seen": "2023-07-20 21:48:48",
        "last_seen": "2023-07-20 21:48:48",
        "ip_address": "199.59.243.224",
        "type": "IPv4"
    },
    {
        "domain": "istaliya.com",
        "count": "10",
        "first_seen": "2019-06-05 11:46:00",
        "last_seen": "2019-06-15 15:10:54",
        "ip_address": "209.99.40.222",
        "type": "IPv4"
    },
    {
        "domain": "istaliya.com",
        "count": "12",
        "first_seen": "2019-06-04 10:54:13",
        "last_seen": "2019-06-15 15:10:52",
        "ip_address": "209.99.40.223",
        "type": "IPv4"
    }
]