[
    {
        "domain": "jbtd4pb7lg.newaidpurchase.ru",
        "count": "2",
        "first_seen": "2015-05-24 20:03:59",
        "last_seen": "2015-05-24 20:03:59",
        "ip_address": "62.76.184.73",
        "type": "IPv4"
    },
    {
        "domain": "jbtd4pb7lg.newaidpurchase.ru",
        "count": "3",
        "first_seen": "2015-05-24 14:39:55",
        "last_seen": "2015-05-24 14:39:55",
        "ip_address": "91.200.12.17",
        "type": "IPv4"
    },
    {
        "domain": "jbtd4pb7lg.newaidpurchase.ru",
        "count": "3",
        "first_seen": "2015-05-24 20:19:56",
        "last_seen": "2015-05-25 01:53:36",
        "ip_address": "91.213.233.72",
        "type": "IPv4"
    }
]