[
    {
        "domain": "kinmen.phxun.cn",
        "count": "1400",
        "first_seen": "2022-07-01 19:32:26",
        "last_seen": "2022-07-26 01:43:56",
        "ip_address": "47.91.170.222",
        "type": "IPv4"
    },
    {
        "domain": "kinmen.phxun.cn",
        "count": "1150",
        "first_seen": "2022-06-03 18:05:42",
        "last_seen": "2022-06-10 03:53:02",
        "ip_address": "149.57.221.245",
        "type": "IPv4"
    },
    {
        "domain": "kinmen.phxun.cn",
        "count": "16",
        "first_seen": "2023-04-11 07:00:27",
        "last_seen": "2023-09-14 23:04:19",
        "ip_address": "164.88.122.72",
        "type": "IPv4"
    },
    {
        "domain": "kinmen.phxun.cn",
        "count": "19",
        "first_seen": "2023-11-08 15:47:43",
        "last_seen": "2023-12-25 03:02:10",
        "ip_address": "168.76.253.222",
        "type": "IPv4"
    }
]