[
    {
        "domain": "kr9210x1rc.magicremedyshop.ru",
        "count": "2",
        "first_seen": "2015-05-21 03:35:14",
        "last_seen": "2015-05-21 03:35:14",
        "ip_address": "50.192.246.250",
        "type": "IPv4"
    },
    {
        "domain": "kr9210x1rc.magicremedyshop.ru",
        "count": "3",
        "first_seen": "2015-05-20 18:26:36",
        "last_seen": "2015-05-20 19:11:55",
        "ip_address": "91.200.12.17",
        "type": "IPv4"
    },
    {
        "domain": "kr9210x1rc.magicremedyshop.ru",
        "count": "6",
        "first_seen": "2015-05-21 06:40:02",
        "last_seen": "2015-05-21 13:42:20",
        "ip_address": "91.213.233.72",
        "type": "IPv4"
    },
    {
        "domain": "kr9210x1rc.magicremedyshop.ru",
        "count": "2",
        "first_seen": "2015-05-21 03:35:14",
        "last_seen": "2015-05-21 03:35:14",
        "ip_address": "95.31.192.232",
        "type": "IPv4"
    },
    {
        "domain": "kr9210x1rc.magicremedyshop.ru",
        "count": "7",
        "first_seen": "2015-05-20 21:49:04",
        "last_seen": "2015-05-23 17:36:24",
        "ip_address": "95.84.156.43",
        "type": "IPv4"
    }
]