[
    {
        "domain": "netstation2-aplus-co-jp.8983836.com",
        "count": "417",
        "first_seen": "2023-01-24 14:51:20",
        "last_seen": "2023-02-11 22:44:08",
        "ip_address": "104.21.6.221",
        "type": "IPv4"
    },
    {
        "domain": "netstation2-aplus-co-jp.8983836.com",
        "count": "417",
        "first_seen": "2023-01-24 14:51:20",
        "last_seen": "2023-02-11 22:44:08",
        "ip_address": "172.67.135.83",
        "type": "IPv4"
    },
    {
        "domain": "netstation2-aplus-co-jp.8983836.com",
        "count": "9",
        "first_seen": "2023-01-24 15:37:22",
        "last_seen": "2023-01-24 19:59:44",
        "ip_address": "188.114.96.14",
        "type": "IPv4"
    },
    {
        "domain": "netstation2-aplus-co-jp.8983836.com",
        "count": "9",
        "first_seen": "2023-01-24 15:37:22",
        "last_seen": "2023-01-24 19:59:44",
        "ip_address": "188.114.97.14",
        "type": "IPv4"
    },
    {
        "domain": "netstation2-aplus-co-jp.8983836.com",
        "count": "1",
        "first_seen": "2023-01-24 15:37:23",
        "last_seen": "2023-01-24 15:37:23",
        "ip_address": "2a06:98c1:3120::e",
        "type": "IPv6"
    },
    {
        "domain": "netstation2-aplus-co-jp.8983836.com",
        "count": "1",
        "first_seen": "2023-01-24 15:37:23",
        "last_seen": "2023-01-24 15:37:23",
        "ip_address": "2a06:98c1:3121::e",
        "type": "IPv6"
    }
]