[
    {
        "domain": "oi57i.magicremedyshop.ru",
        "count": "4",
        "first_seen": "2015-05-16 16:12:49",
        "last_seen": "2015-05-16 18:22:41",
        "ip_address": "91.200.12.17",
        "type": "IPv4"
    },
    {
        "domain": "oi57i.magicremedyshop.ru",
        "count": "2",
        "first_seen": "2015-05-17 01:50:26",
        "last_seen": "2015-05-17 01:50:26",
        "ip_address": "95.31.192.232",
        "type": "IPv4"
    },
    {
        "domain": "oi57i.magicremedyshop.ru",
        "count": "4",
        "first_seen": "2015-05-16 06:33:57",
        "last_seen": "2015-05-16 07:41:40",
        "ip_address": "95.84.156.43",
        "type": "IPv4"
    },
    {
        "domain": "oi57i.magicremedyshop.ru",
        "count": "4",
        "first_seen": "2015-05-16 12:54:10",
        "last_seen": "2015-05-16 20:17:03",
        "ip_address": "217.174.100.238",
        "type": "IPv4"
    }
]