[
    {
        "domain": "openid.thjgkx.icu",
        "count": "48",
        "first_seen": "2020-09-22 09:44:36",
        "last_seen": "2020-09-26 15:31:26",
        "ip_address": "104.31.68.240",
        "type": "IPv4"
    },
    {
        "domain": "openid.thjgkx.icu",
        "count": "48",
        "first_seen": "2020-09-22 09:44:36",
        "last_seen": "2020-09-26 15:31:26",
        "ip_address": "104.31.69.240",
        "type": "IPv4"
    },
    {
        "domain": "openid.thjgkx.icu",
        "count": "48",
        "first_seen": "2020-09-22 09:44:36",
        "last_seen": "2020-09-26 15:31:26",
        "ip_address": "172.67.160.200",
        "type": "IPv4"
    },
    {
        "domain": "openid.thjgkx.icu",
        "count": "4",
        "first_seen": "2020-09-22 09:44:36",
        "last_seen": "2020-09-23 08:53:43",
        "ip_address": "2606:4700:3030::681f:45f0",
        "type": "IPv6"
    },
    {
        "domain": "openid.thjgkx.icu",
        "count": "4",
        "first_seen": "2020-09-22 09:44:36",
        "last_seen": "2020-09-23 08:53:43",
        "ip_address": "2606:4700:3032::ac43:a0c8",
        "type": "IPv6"
    },
    {
        "domain": "openid.thjgkx.icu",
        "count": "4",
        "first_seen": "2020-09-22 09:44:36",
        "last_seen": "2020-09-23 08:53:43",
        "ip_address": "2606:4700:3034::681f:44f0",
        "type": "IPv6"
    }
]