[
    {
        "domain": "phpsrv.ic.edu.lb",
        "count": "23",
        "first_seen": "2016-05-07 16:11:58",
        "last_seen": "2016-06-10 22:39:29",
        "ip_address": "77.42.250.203",
        "type": "IPv4"
    },
    {
        "domain": "phpsrv.ic.edu.lb",
        "count": "851",
        "first_seen": "2016-06-14 06:15:53",
        "last_seen": "2024-01-09 03:13:44",
        "ip_address": "77.42.250.205",
        "type": "IPv4"
    },
    {
        "domain": "phpsrv.ic.edu.lb",
        "count": "314",
        "first_seen": "2015-03-10 07:59:14",
        "last_seen": "2016-05-03 15:28:46",
        "ip_address": "89.108.151.10",
        "type": "IPv4"
    }
]