[
    {
        "domain": "ruiukentt.erfa.site",
        "count": "12",
        "first_seen": "2023-06-30 00:48:53",
        "last_seen": "2023-12-18 09:43:57",
        "ip_address": "35.186.223.180",
        "type": "IPv4"
    },
    {
        "domain": "ruiukentt.erfa.site",
        "count": "1",
        "first_seen": "2023-05-19 11:14:43",
        "last_seen": "2023-05-19 11:14:43",
        "ip_address": "127.0.0.1",
        "type": "IPv4"
    },
    {
        "domain": "ruiukentt.erfa.site",
        "count": "5",
        "first_seen": "2021-01-07 17:41:09",
        "last_seen": "2021-01-08 02:14:07",
        "ip_address": "192.236.146.249",
        "type": "IPv4"
    }
]