[
    {
        "domain": "southwestgriefandlosscentre.com.au",
        "count": "393",
        "first_seen": "2017-11-20 01:34:24",
        "last_seen": "2020-08-17 06:18:19",
        "ip_address": "27.123.31.81",
        "type": "IPv4"
    },
    {
        "domain": "southwestgriefandlosscentre.com.au",
        "count": "1",
        "first_seen": "2017-08-02 06:17:11",
        "last_seen": "2017-08-02 06:17:11",
        "ip_address": "27.124.118.252",
        "type": "IPv4"
    },
    {
        "domain": "southwestgriefandlosscentre.com.au",
        "count": "2103",
        "first_seen": "2020-08-24 06:21:32",
        "last_seen": "2024-01-18 06:15:51",
        "ip_address": "122.201.66.57",
        "type": "IPv4"
    },
    {
        "domain": "southwestgriefandlosscentre.com.au",
        "count": "282",
        "first_seen": "2020-09-26 02:57:46",
        "last_seen": "2024-01-18 11:38:05",
        "ip_address": "2405:3f00:a222:bbbb:bba1:31:ffff:ffff",
        "type": "IPv6"
    }
]