[
    {
        "domain": "w-transfers.host",
        "count": "11",
        "first_seen": "2020-07-06 07:36:11",
        "last_seen": "2020-07-07 12:50:38",
        "ip_address": "85.204.74.153",
        "type": "IPv4"
    },
    {
        "domain": "w-transfers.host",
        "count": "13",
        "first_seen": "2020-08-17 20:59:08",
        "last_seen": "2020-08-27 11:29:31",
        "ip_address": "93.113.45.37",
        "type": "IPv4"
    },
    {
        "domain": "w-transfers.host",
        "count": "6",
        "first_seen": "2021-06-17 18:14:21",
        "last_seen": "2021-07-26 05:01:25",
        "ip_address": "99.83.154.118",
        "type": "IPv4"
    },
    {
        "domain": "w-transfers.host",
        "count": "27",
        "first_seen": "2020-06-17 08:24:31",
        "last_seen": "2020-07-01 03:48:48",
        "ip_address": "107.173.194.231",
        "type": "IPv4"
    },
    {
        "domain": "w-transfers.host",
        "count": "22",
        "first_seen": "2020-07-24 03:32:22",
        "last_seen": "2020-08-09 01:55:51",
        "ip_address": "192.3.193.16",
        "type": "IPv4"
    },
    {
        "domain": "w-transfers.host",
        "count": "32",
        "first_seen": "2021-02-16 09:29:20",
        "last_seen": "2021-03-07 11:48:21",
        "ip_address": "192.236.163.153",
        "type": "IPv4"
    }
]