[
    {
        "domain": "www-amazon-co-jp.meitesibangwei.net.cn",
        "count": "35",
        "first_seen": "2022-03-28 10:16:59",
        "last_seen": "2022-09-09 17:06:25",
        "ip_address": "0.0.0.0",
        "type": "IPv4"
    },
    {
        "domain": "www-amazon-co-jp.meitesibangwei.net.cn",
        "count": "59",
        "first_seen": "2021-12-02 14:04:19",
        "last_seen": "2021-12-25 23:31:25",
        "ip_address": "104.21.24.33",
        "type": "IPv4"
    },
    {
        "domain": "www-amazon-co-jp.meitesibangwei.net.cn",
        "count": "59",
        "first_seen": "2021-12-02 14:04:19",
        "last_seen": "2021-12-25 23:31:25",
        "ip_address": "172.67.216.187",
        "type": "IPv4"
    }
]