[
    {
        "domain": "www.myjacasesoeb.myjaccocasoeb.yxfspd.xyz",
        "count": "974",
        "first_seen": "2022-10-01 00:48:07",
        "last_seen": "2022-11-07 00:03:16",
        "ip_address": "47.91.170.222",
        "type": "IPv4"
    },
    {
        "domain": "www.myjacasesoeb.myjaccocasoeb.yxfspd.xyz",
        "count": "1238",
        "first_seen": "2022-07-12 20:10:22",
        "last_seen": "2022-08-06 12:35:45",
        "ip_address": "198.12.89.143",
        "type": "IPv4"
    }
]