[
    {
        "domain": "www.saissonarard.co.jp.zj318.cn",
        "count": "2",
        "first_seen": "2023-07-24 01:16:50",
        "last_seen": "2023-07-24 01:16:50",
        "ip_address": "47.91.170.222",
        "type": "IPv4"
    },
    {
        "domain": "www.saissonarard.co.jp.zj318.cn",
        "count": "8",
        "first_seen": "2023-09-18 21:42:45",
        "last_seen": "2023-12-28 02:15:23",
        "ip_address": "107.149.15.231",
        "type": "IPv4"
    },
    {
        "domain": "www.saissonarard.co.jp.zj318.cn",
        "count": "46",
        "first_seen": "2023-05-20 16:08:05",
        "last_seen": "2023-05-23 10:48:06",
        "ip_address": "192.161.179.225",
        "type": "IPv4"
    }
]