[
    {
        "domain": "www.scvd-cnnd.caoscod.com",
        "count": "15",
        "first_seen": "2021-09-18 01:52:45",
        "last_seen": "2022-08-28 19:11:06",
        "ip_address": "137.184.75.217",
        "type": "IPv4"
    },
    {
        "domain": "www.scvd-cnnd.caoscod.com",
        "count": "169",
        "first_seen": "2021-09-16 21:29:55",
        "last_seen": "2021-09-17 13:37:22",
        "ip_address": "154.30.198.156",
        "type": "IPv4"
    },
    {
        "domain": "www.scvd-cnnd.caoscod.com",
        "count": "23",
        "first_seen": "2022-09-17 04:30:56",
        "last_seen": "2022-10-12 04:59:44",
        "ip_address": "199.59.242.150",
        "type": "IPv4"
    },
    {
        "domain": "www.scvd-cnnd.caoscod.com",
        "count": "8",
        "first_seen": "2022-09-17 04:30:56",
        "last_seen": "2022-10-24 06:55:14",
        "ip_address": "199.59.242.150",
        "type": "IPv4"
    },
    {
        "domain": "www.scvd-cnnd.caoscod.com",
        "count": "7",
        "first_seen": "2022-09-17 04:30:56",
        "last_seen": "2022-09-17 17:08:29",
        "ip_address": "199.59.242.150",
        "type": "IPv4"
    }
]