[
    {
        "domain": "www.anzcam-co-jp.amazaon.quftas.top",
        "count": "57",
        "first_seen": "2022-11-24 20:00:08",
        "last_seen": "2022-11-25 07:31:30",
        "ip_address": "155.94.135.45",
        "type": "IPv4"
    },
    {
        "domain": "www.anzcam-co-jp.amazaon.quftas.top",
        "count": "60",
        "first_seen": "2022-11-26 08:16:45",
        "last_seen": "2023-01-26 17:49:36",
        "ip_address": "155.94.169.166",
        "type": "IPv4"
    },
    {
        "domain": "www.anzcam-co-jp.amazaon.quftas.top",
        "count": "5",
        "first_seen": "2022-11-25 18:32:12",
        "last_seen": "2022-11-26 03:30:00",
        "ip_address": "204.44.83.152",
        "type": "IPv4"
    }
]