[
    {
        "domain": "www.sfkayaking.com",
        "count": "1",
        "first_seen": "2022-08-02 02:03:56",
        "last_seen": "2022-08-02 02:03:56",
        "ip_address": "103.76.87.41",
        "type": "IPv4"
    },
    {
        "domain": "www.sfkayaking.com",
        "count": "12",
        "first_seen": "2022-11-22 08:00:45",
        "last_seen": "2022-11-26 19:48:57",
        "ip_address": "103.149.91.238",
        "type": "IPv4"
    },
    {
        "domain": "www.sfkayaking.com",
        "count": "5",
        "first_seen": "2022-08-24 15:40:36",
        "last_seen": "2022-10-06 10:51:02",
        "ip_address": "149.127.215.46",
        "type": "IPv4"
    },
    {
        "domain": "www.sfkayaking.com",
        "count": "356",
        "first_seen": "2023-04-17 12:57:23",
        "last_seen": "2023-04-27 17:50:45",
        "ip_address": "155.94.178.73",
        "type": "IPv4"
    }
]