[
    {
        "domain": "www.aoseun-asoesneonm.03nm.top",
        "count": "1",
        "first_seen": "2022-10-10 18:07:26",
        "last_seen": "2022-10-10 18:07:26",
        "ip_address": "47.91.170.222",
        "type": "IPv4"
    },
    {
        "domain": "www.aoseun-asoesneonm.03nm.top",
        "count": "10",
        "first_seen": "2023-12-05 06:18:55",
        "last_seen": "2024-01-11 01:55:02",
        "ip_address": "172.121.33.136",
        "type": "IPv4"
    },
    {
        "domain": "www.aoseun-asoesneonm.03nm.top",
        "count": "751",
        "first_seen": "2022-05-06 15:44:44",
        "last_seen": "2022-05-14 12:23:16",
        "ip_address": "198.46.132.207",
        "type": "IPv4"
    }
]