[
    {
        "domain": "www.epos-carb.vip",
        "count": "3",
        "first_seen": "2022-04-13 00:13:40",
        "last_seen": "2022-04-29 15:07:37",
        "ip_address": "47.91.170.222",
        "type": "IPv4"
    },
    {
        "domain": "www.epos-carb.vip",
        "count": "76",
        "first_seen": "2021-04-10 13:55:34",
        "last_seen": "2022-04-10 08:58:52",
        "ip_address": "198.12.121.164",
        "type": "IPv4"
    },
    {
        "domain": "www.epos-carb.vip",
        "count": "1502",
        "first_seen": "2021-04-09 18:23:26",
        "last_seen": "2021-04-10 13:49:28",
        "ip_address": "198.12.121.166",
        "type": "IPv4"
    }
]