[
    {
        "domain": "www.a.mceseirn.com",
        "count": "87",
        "first_seen": "2021-12-14 21:11:50",
        "last_seen": "2021-12-17 01:12:52",
        "ip_address": "23.95.122.118",
        "type": "IPv4"
    },
    {
        "domain": "www.a.mceseirn.com",
        "count": "2",
        "first_seen": "2023-01-04 12:48:43",
        "last_seen": "2023-01-11 14:24:34",
        "ip_address": "199.59.242.150",
        "type": "IPv4"
    },
    {
        "domain": "www.a.mceseirn.com",
        "count": "1",
        "first_seen": "2022-12-20 11:12:02",
        "last_seen": "2022-12-20 11:12:02",
        "ip_address": "199.59.242.150",
        "type": "IPv4"
    },
    {
        "domain": "www.a.mceseirn.com",
        "count": "4",
        "first_seen": "2022-12-20 11:12:02",
        "last_seen": "2023-01-11 14:24:34",
        "ip_address": "199.59.242.150",
        "type": "IPv4"
    }
]