[
    {
        "domain": "www.s.mectaoacd.com",
        "count": "112",
        "first_seen": "2021-12-08 21:45:11",
        "last_seen": "2021-12-10 01:18:42",
        "ip_address": "198.144.176.204",
        "type": "IPv4"
    },
    {
        "domain": "www.s.mectaoacd.com",
        "count": "3",
        "first_seen": "2022-12-26 01:47:04",
        "last_seen": "2023-01-15 05:25:39",
        "ip_address": "199.59.242.150",
        "type": "IPv4"
    },
    {
        "domain": "www.s.mectaoacd.com",
        "count": "4",
        "first_seen": "2022-12-26 01:47:04",
        "last_seen": "2023-01-15 05:25:39",
        "ip_address": "199.59.242.150",
        "type": "IPv4"
    }
]