[
    {
        "domain": "www.saciseancs-co-jp.saisnascen.mqoyrx.top",
        "count": "1",
        "first_seen": "2023-02-10 05:30:22",
        "last_seen": "2023-02-10 05:30:22",
        "ip_address": "47.91.170.222",
        "type": "IPv4"
    },
    {
        "domain": "www.saciseancs-co-jp.saisnascen.mqoyrx.top",
        "count": "56",
        "first_seen": "2022-11-26 18:34:14",
        "last_seen": "2022-11-27 09:29:39",
        "ip_address": "204.44.99.56",
        "type": "IPv4"
    }
]