[
    {
        "domain": "www.famipay.famldlgli.dgwanlizy.cn",
        "count": "11804",
        "first_seen": "2023-07-22 21:01:53",
        "last_seen": "2023-08-21 22:17:44",
        "ip_address": "47.91.170.222",
        "type": "IPv4"
    },
    {
        "domain": "www.famipay.famldlgli.dgwanlizy.cn",
        "count": "150",
        "first_seen": "2023-04-25 23:48:33",
        "last_seen": "2023-04-26 12:34:02",
        "ip_address": "172.245.214.75",
        "type": "IPv4"
    },
    {
        "domain": "www.famipay.famldlgli.dgwanlizy.cn",
        "count": "3606",
        "first_seen": "2023-04-26 13:50:18",
        "last_seen": "2023-06-01 15:38:51",
        "ip_address": "192.3.223.214",
        "type": "IPv4"
    }
]