[
    {
        "domain": "www.myjascesoccsaaseseb.mseyjcaacosearescoooseccsooeb.mfwrsg.top",
        "count": "498",
        "first_seen": "2022-07-15 19:14:45",
        "last_seen": "2022-07-29 14:52:54",
        "ip_address": "107.174.138.182",
        "type": "IPv4"
    },
    {
        "domain": "www.myjascesoccsaaseseb.mseyjcaacosearescoooseccsooeb.mfwrsg.top",
        "count": "5",
        "first_seen": "2022-08-14 07:58:51",
        "last_seen": "2022-08-15 16:00:44",
        "ip_address": "124.156.132.238",
        "type": "IPv4"
    },
    {
        "domain": "www.myjascesoccsaaseseb.mseyjcaacosearescoooseccsooeb.mfwrsg.top",
        "count": "82",
        "first_seen": "2022-11-21 10:02:34",
        "last_seen": "2022-11-21 10:02:35",
        "ip_address": "154.83.15.226",
        "type": "IPv4"
    }
]