[
    {
        "domain": "www.c.moeccroci.com",
        "count": "107",
        "first_seen": "2021-12-06 20:57:17",
        "last_seen": "2021-12-08 11:11:10",
        "ip_address": "23.95.122.118",
        "type": "IPv4"
    },
    {
        "domain": "www.c.moeccroci.com",
        "count": "5",
        "first_seen": "2022-12-19 17:47:49",
        "last_seen": "2023-01-10 12:14:55",
        "ip_address": "199.59.242.150",
        "type": "IPv4"
    },
    {
        "domain": "www.c.moeccroci.com",
        "count": "6",
        "first_seen": "2022-12-19 17:47:49",
        "last_seen": "2023-01-10 12:14:55",
        "ip_address": "199.59.242.150",
        "type": "IPv4"
    }
]