[
    {
        "domain": "www.azzoman.aozmamc.com",
        "count": "217",
        "first_seen": "2021-10-11 21:54:05",
        "last_seen": "2022-07-19 01:18:54",
        "ip_address": "198.12.81.113",
        "type": "IPv4"
    },
    {
        "domain": "www.azzoman.aozmamc.com",
        "count": "2",
        "first_seen": "2022-10-13 20:58:34",
        "last_seen": "2022-10-15 23:29:20",
        "ip_address": "199.59.242.150",
        "type": "IPv4"
    },
    {
        "domain": "www.azzoman.aozmamc.com",
        "count": "3",
        "first_seen": "2022-10-13 20:58:34",
        "last_seen": "2022-10-13 20:58:40",
        "ip_address": "199.59.242.150",
        "type": "IPv4"
    }
]