[
    {
        "domain": "www.myjeeseosiaescrcseocoseebieo.socenmaseocyeueoccesoesjcaoseeseb.falp.co",
        "count": "69",
        "first_seen": "2022-08-02 05:09:35",
        "last_seen": "2022-08-03 17:24:15",
        "ip_address": "47.91.170.222",
        "type": "IPv4"
    },
    {
        "domain": "www.myjeeseosiaescrcseocoseebieo.socenmaseocyeueoccesoesjcaoseeseb.falp.co",
        "count": "240",
        "first_seen": "2022-07-27 04:38:06",
        "last_seen": "2022-08-02 03:55:00",
        "ip_address": "107.174.138.160",
        "type": "IPv4"
    }
]