[
    {
        "domain": "www.chezdioresto.com",
        "count": "4",
        "first_seen": "2019-02-11 03:11:10",
        "last_seen": "2019-04-08 00:07:33",
        "ip_address": "5.79.79.209",
        "type": "IPv4"
    },
    {
        "domain": "www.chezdioresto.com",
        "count": "2",
        "first_seen": "2019-08-16 01:55:35",
        "last_seen": "2019-08-16 01:55:35",
        "ip_address": "5.79.79.211",
        "type": "IPv4"
    },
    {
        "domain": "www.chezdioresto.com",
        "count": "2",
        "first_seen": "2019-02-16 02:49:38",
        "last_seen": "2019-02-16 02:49:38",
        "ip_address": "5.79.79.212",
        "type": "IPv4"
    },
    {
        "domain": "www.chezdioresto.com",
        "count": "8",
        "first_seen": "2018-11-29 06:00:53",
        "last_seen": "2019-01-22 06:21:55",
        "ip_address": "108.59.12.98",
        "type": "IPv4"
    },
    {
        "domain": "www.chezdioresto.com",
        "count": "8",
        "first_seen": "2018-12-22 20:47:54",
        "last_seen": "2019-04-15 14:23:20",
        "ip_address": "108.59.12.100",
        "type": "IPv4"
    },
    {
        "domain": "www.chezdioresto.com",
        "count": "6",
        "first_seen": "2018-10-31 15:50:48",
        "last_seen": "2019-03-03 04:52:29",
        "ip_address": "108.59.12.101",
        "type": "IPv4"
    },
    {
        "domain": "www.chezdioresto.com",
        "count": "3",
        "first_seen": "2019-03-16 02:43:11",
        "last_seen": "2019-03-16 07:28:58",
        "ip_address": "199.115.115.118",
        "type": "IPv4"
    },
    {
        "domain": "www.chezdioresto.com",
        "count": "209",
        "first_seen": "2022-08-04 02:37:48",
        "last_seen": "2022-08-05 02:05:56",
        "ip_address": "204.152.210.230",
        "type": "IPv4"
    }
]