[
    {
        "domain": "www.aceomse.amsocnc.com",
        "count": "351",
        "first_seen": "2021-09-09 19:15:46",
        "last_seen": "2022-08-03 11:17:49",
        "ip_address": "155.235.250.219",
        "type": "IPv4"
    },
    {
        "domain": "www.aceomse.amsocnc.com",
        "count": "5",
        "first_seen": "2022-09-09 19:43:43",
        "last_seen": "2022-10-06 10:07:59",
        "ip_address": "199.59.242.150",
        "type": "IPv4"
    },
    {
        "domain": "www.aceomse.amsocnc.com",
        "count": "1",
        "first_seen": "2022-10-12 06:44:23",
        "last_seen": "2022-10-12 06:44:23",
        "ip_address": "199.59.242.150",
        "type": "IPv4"
    },
    {
        "domain": "www.aceomse.amsocnc.com",
        "count": "1",
        "first_seen": "2022-10-12 06:44:23",
        "last_seen": "2022-10-12 06:44:23",
        "ip_address": "199.59.242.150",
        "type": "IPv4"
    }
]