[
    {
        "domain": "www.saisosncarcrd.co.jp.tremty.top",
        "count": "1",
        "first_seen": "2023-05-12 12:32:20",
        "last_seen": "2023-05-12 12:32:20",
        "ip_address": "103.120.80.111",
        "type": "IPv4"
    },
    {
        "domain": "www.saisosncarcrd.co.jp.tremty.top",
        "count": "3",
        "first_seen": "2023-04-10 23:10:32",
        "last_seen": "2023-04-11 00:58:05",
        "ip_address": "134.122.123.200",
        "type": "IPv4"
    },
    {
        "domain": "www.saisosncarcrd.co.jp.tremty.top",
        "count": "6",
        "first_seen": "2023-04-11 04:10:01",
        "last_seen": "2023-04-11 05:48:55",
        "ip_address": "157.230.191.189",
        "type": "IPv4"
    }
]