[
    {
        "domain": "www.vpassfeaofmdug.bsofurjaie.com",
        "count": "65",
        "first_seen": "2022-08-08 18:49:31",
        "last_seen": "2022-08-09 21:23:33",
        "ip_address": "23.94.208.188",
        "type": "IPv4"
    },
    {
        "domain": "www.vpassfeaofmdug.bsofurjaie.com",
        "count": "1",
        "first_seen": "2023-04-15 14:41:22",
        "last_seen": "2023-04-15 14:41:22",
        "ip_address": "70.32.1.32",
        "type": "IPv4"
    },
    {
        "domain": "www.vpassfeaofmdug.bsofurjaie.com",
        "count": "29",
        "first_seen": "2022-08-24 11:26:25",
        "last_seen": "2023-09-07 18:13:31",
        "ip_address": "103.224.182.242",
        "type": "IPv4"
    }
]