[
    {
        "domain": "www.raketonccasecasord.arkascoseutsen.bgjjoi.top",
        "count": "1",
        "first_seen": "2022-11-28 23:36:27",
        "last_seen": "2022-11-29 05:32:51",
        "ip_address": "47.91.170.222",
        "type": "IPv4"
    },
    {
        "domain": "www.raketonccasecasord.arkascoseutsen.bgjjoi.top",
        "count": "36",
        "first_seen": "2022-11-21 11:37:03",
        "last_seen": "2022-11-21 11:37:03",
        "ip_address": "104.21.89.165",
        "type": "IPv4"
    },
    {
        "domain": "www.raketonccasecasord.arkascoseutsen.bgjjoi.top",
        "count": "36",
        "first_seen": "2022-11-21 11:37:03",
        "last_seen": "2022-11-21 11:37:03",
        "ip_address": "172.67.189.247",
        "type": "IPv4"
    },
    {
        "domain": "www.raketonccasecasord.arkascoseutsen.bgjjoi.top",
        "count": "282",
        "first_seen": "2022-07-14 19:59:52",
        "last_seen": "2022-07-22 16:54:48",
        "ip_address": "107.175.3.36",
        "type": "IPv4"
    }
]