[
    {
        "domain": "www.chlbanbamk.youcompound.com",
        "count": "21852",
        "first_seen": "2023-10-06 10:35:11",
        "last_seen": "2024-01-18 03:58:20",
        "ip_address": "38.6.91.194",
        "type": "IPv4"
    },
    {
        "domain": "www.chlbanbamk.youcompound.com",
        "count": "2282",
        "first_seen": "2023-09-05 20:56:07",
        "last_seen": "2023-09-16 04:41:38",
        "ip_address": "38.40.203.71",
        "type": "IPv4"
    },
    {
        "domain": "www.chlbanbamk.youcompound.com",
        "count": "13831",
        "first_seen": "2023-07-21 09:52:16",
        "last_seen": "2023-09-05 19:15:36",
        "ip_address": "38.40.221.102",
        "type": "IPv4"
    },
    {
        "domain": "www.chlbanbamk.youcompound.com",
        "count": "1349",
        "first_seen": "2023-09-16 05:25:07",
        "last_seen": "2023-09-26 10:52:46",
        "ip_address": "38.48.187.134",
        "type": "IPv4"
    },
    {
        "domain": "www.chlbanbamk.youcompound.com",
        "count": "4094",
        "first_seen": "2023-07-11 01:50:04",
        "last_seen": "2023-07-21 09:44:59",
        "ip_address": "38.63.107.23",
        "type": "IPv4"
    },
    {
        "domain": "www.chlbanbamk.youcompound.com",
        "count": "1680",
        "first_seen": "2023-09-26 11:35:26",
        "last_seen": "2023-10-06 09:48:45",
        "ip_address": "38.163.78.233",
        "type": "IPv4"
    },
    {
        "domain": "www.chlbanbamk.youcompound.com",
        "count": "2205",
        "first_seen": "2023-07-04 20:40:04",
        "last_seen": "2023-07-11 01:37:26",
        "ip_address": "107.164.140.142",
        "type": "IPv4"
    },
    {
        "domain": "www.chlbanbamk.youcompound.com",
        "count": "17",
        "first_seen": "2023-05-28 13:29:32",
        "last_seen": "2023-05-28 23:48:32",
        "ip_address": "198.55.103.55",
        "type": "IPv4"
    }
]