[
    {
        "domain": "www.honest-horse.com",
        "count": "1823",
        "first_seen": "2018-06-23 08:59:15",
        "last_seen": "2021-01-07 22:45:37",
        "ip_address": "107.180.63.53",
        "type": "IPv4"
    },
    {
        "domain": "www.honest-horse.com",
        "count": "1232",
        "first_seen": "2018-07-19 15:46:32",
        "last_seen": "2018-12-10 12:42:04",
        "ip_address": "137.175.77.20",
        "type": "IPv4"
    },
    {
        "domain": "www.honest-horse.com",
        "count": "1",
        "first_seen": "2012-06-20 17:40:55",
        "last_seen": "2012-06-20 17:40:55",
        "ip_address": "180.186.9.173",
        "type": "IPv4"
    }
]