[
    {
        "domain": "www.vscioseacasevi.viacvavacosarr.zxj9002.xyz",
        "count": "131",
        "first_seen": "2022-09-05 07:45:10",
        "last_seen": "2022-09-07 02:08:10",
        "ip_address": "107.172.4.180",
        "type": "IPv4"
    },
    {
        "domain": "www.vscioseacasevi.viacvavacosarr.zxj9002.xyz",
        "count": "131",
        "first_seen": "2022-09-05 07:45:10",
        "last_seen": "2022-09-07 02:08:10",
        "ip_address": "192.3.173.114",
        "type": "IPv4"
    },
    {
        "domain": "www.vscioseacasevi.viacvavacosarr.zxj9002.xyz",
        "count": "448",
        "first_seen": "2022-09-07 03:45:17",
        "last_seen": "2022-09-17 16:48:14",
        "ip_address": "107.172.4.180",
        "type": "IPv4"
    },
    {
        "domain": "www.vscioseacasevi.viacvavacosarr.zxj9002.xyz",
        "count": "448",
        "first_seen": "2022-09-07 03:45:17",
        "last_seen": "2022-09-17 16:48:14",
        "ip_address": "192.3.173.114",
        "type": "IPv4"
    },
    {
        "domain": "www.vscioseacasevi.viacvavacosarr.zxj9002.xyz",
        "count": "448",
        "first_seen": "2022-09-07 03:45:17",
        "last_seen": "2022-09-17 16:48:14",
        "ip_address": "192.227.132.51",
        "type": "IPv4"
    }
]