[
    {
        "domain": "www.kueronekayacotn-co-jp.kuerocekayacoto.nvqbnq.top",
        "count": "9",
        "first_seen": "2023-03-19 12:12:06",
        "last_seen": "2023-03-28 13:18:00",
        "ip_address": "47.91.170.222",
        "type": "IPv4"
    },
    {
        "domain": "www.kueronekayacotn-co-jp.kuerocekayacoto.nvqbnq.top",
        "count": "24",
        "first_seen": "2023-02-22 22:00:37",
        "last_seen": "2023-03-09 11:05:18",
        "ip_address": "155.94.182.154",
        "type": "IPv4"
    }
]