[
    {
        "domain": "www1.z675iino.cyou",
        "count": "37",
        "first_seen": "2023-06-24 08:18:52",
        "last_seen": "2023-06-26 00:14:39",
        "ip_address": "51.81.58.60",
        "type": "IPv4"
    },
    {
        "domain": "www1.z675iino.cyou",
        "count": "9",
        "first_seen": "2023-06-26 11:31:29",
        "last_seen": "2023-07-03 19:04:10",
        "ip_address": "194.36.170.185",
        "type": "IPv4"
    },
    {
        "domain": "www1.z675iino.cyou",
        "count": "10",
        "first_seen": "2023-06-22 04:34:41",
        "last_seen": "2023-06-23 09:11:19",
        "ip_address": "198.251.88.216",
        "type": "IPv4"
    }
]