[
    {
        "domain": "www_aeon_co_jp.dzg8w.cn",
        "count": "51",
        "first_seen": "2021-09-23 15:35:45",
        "last_seen": "2021-09-24 22:20:18",
        "ip_address": "104.21.19.109",
        "type": "IPv4"
    },
    {
        "domain": "www_aeon_co_jp.dzg8w.cn",
        "count": "51",
        "first_seen": "2021-09-23 15:35:45",
        "last_seen": "2021-09-24 22:20:18",
        "ip_address": "172.67.185.249",
        "type": "IPv4"
    },
    {
        "domain": "www_aeon_co_jp.dzg8w.cn",
        "count": "3",
        "first_seen": "2021-09-23 16:48:38",
        "last_seen": "2021-09-24 22:18:44",
        "ip_address": "2606:4700:3037::6815:136d",
        "type": "IPv6"
    },
    {
        "domain": "www_aeon_co_jp.dzg8w.cn",
        "count": "3",
        "first_seen": "2021-09-23 16:48:38",
        "last_seen": "2021-09-24 22:18:44",
        "ip_address": "2606:4700:3037::ac43:b9f9",
        "type": "IPv6"
    }
]